python_readability-0.1.3.dist-info/METADATA
python_readability-0.1.3.dist-info/WHEEL
python_readability-0.1.3.dist-info/entry_points.txt
readability/__init__.py
readability/api/parse.py
readability/impl/__init__.py
readability/impl/parse.cjs
readability/impl/pyodide.py
readability/impl/pythonmonkey.py
readability/utils/cases.py
python_readability-0.1.3.dist-info/RECORD
