Metadata-Version: 2.1
Name: python-readability
Version: 0.1.3
Summary: @mozilla/readability for Python
Requires-Python: >=3.8
Requires-Dist: pythonmonkey-fork~=1.0; sys_platform != "emscripten"
